PickleHandler/PickleHandler.py
PickleHandler/__init__.py
PickleHandler-1.0.11.dist-info/License
PickleHandler-1.0.11.dist-info/METADATA
PickleHandler-1.0.11.dist-info/WHEEL
PickleHandler-1.0.11.dist-info/top_level.txt
PickleHandler-1.0.11.dist-info/RECORD
