Metadata-Version: 2.1
Name: PickleHandler
Version: 1.0.11
Summary: A utility for saving and loading data using pickle with logging functionality.
Home-page: https://github.com/Prbn/PickleHandler
Author: PRBN
Author-email: <career.prabin@gmail.com>
Keywords: python,pickle,save,load,logging
Classifier: Development Status :: 5 - Production/Stable
Classifier: Intended Audience :: Developers
Classifier: Programming Language :: Python :: 3
Classifier: License :: OSI Approved :: MIT License
Classifier: Operating System :: OS Independent
License-File: License
